task3/counter.sv
module counter #(
  parameter WIDTH = 8
)(
  // interface signals
  input  logic             clk,      // clock 
  input  logic             rst,      // reset 
  input  logic             ld,       // load counter from data
  input  logic [WIDTH-1:0] v,        // value to preload
  output logic [WIDTH-1:0] count     // count output
);

always_ff @ (posedge clk)
  if (rst) count <= {WIDTH{1'b0}};
  else     count <= ld ? v : count + {{WIDTH-1{1'b0}},1'b1};
endmodule

task3/counter.vcd
$version Generated by VerilatedVcd $end
$date Thu Oct 19 10:55:30 2023 $end
$timescale 1ps $end

 $scope module TOP $end
  $var wire  1 # clk $end
  $var wire  8 ' count [7:0] $end
  $var wire  1 % ld $end
  $var wire  1 $ rst $end
  $var wire  8 & v [7:0] $end
  $scope module counter $end
   $var wire 32 ( WIDTH [31:0] $end
   $var wire  1 # clk $end
   $var wire  8 ' count [7:0] $end
   $var wire  1 % ld $end
   $var wire  1 $ rst $end
   $var wire  8 & v [7:0] $end
  $upscope $end
 $upscope $end
$enddefinitions $end


#0
1#
0$
0%
b00000000 &
b00000000 '
b00000000000000000000000000001000 (
#1
0#
#2
1#
b00001000 &
b00000001 '
#3
0#
#4
1#
1%
b00000010 '
#5
0#
#6
1#
0%
b00001000 '
#7
0#
#8
1#
b00001001 '
#9
0#
#10
1#
b00001010 '
#11
0#
#12
1#
b00001011 '
#13
0#
#14
1#
b00001100 '
#15
0#
#16
1#
b00001101 '
#17
0#
#18
1#
b00001110 '
#19
0#
#20
1#
1%
b00001111 '
#21
0#
#22
1#
0%
b00001000 '
#23
0#
#24
1#
b00001001 '
#25
0#
#26
1#
b00001010 '
#27
0#
#28
1#
b00001011 '
#29
0#
#30
1#
b00001100 '
#31
0#
#32
1#
1%
b00001101 '
#33
0#
#34
1#
0%
b00001000 '
#35
0#
#36
1#
b00001001 '
#37
0#
#38
1#
b00001010 '
#39
0#
#40
1#
b00001011 '
#41
0#
#42
1#
b00001100 '
#43
0#
#44
1#
b00001101 '
#45
0#
#46
1#
b00001110 '
#47
0#
#48
1#
b00001111 '
#49
0#
#50
1#
b00010000 '
#51
0#
#52
1#
1%
b00010001 '
#53
0#
#54
1#
0%
b00001000 '
#55
0#
#56
1#
1%
b00001001 '
#57
0#
#58
1#
0%
b00001000 '
#59
0#
#60
1#
1%
b00001001 '
#61
0#
#62
1#
b00001000 '
#63
0#
#64
1#
0%
#65
0#
#66
1#
1%
b00001001 '
#67
0#
#68
1#
0%
b00001000 '
#69
0#
#70
1#
b00001001 '
#71
0#
#72
1#
b00001010 '
#73
0#
#74
1#
b00001011 '
#75
0#
#76
1#
b00001100 '
#77
0#
#78
1#
b00001101 '
#79
0#
#80
1#
b00001110 '
#81
0#
#82
1#
b00001111 '
#83
0#
#84
1#
b00010000 '
#85
0#
#86
1#
b00010001 '
#87
0#
#88
1#
b00010010 '
#89
0#
#90
1#
b00010011 '
#91
0#
#92
1#
b00010100 '
#93
0#
#94
1#
b00010101 '
#95
0#
#96
1#
b00010110 '
#97
0#
#98
1#
b00010111 '
#99
0#
#100
1#
b00011000 '
#101
0#
#102
1#
b00011001 '
#103
0#
#104
1#
b00011010 '
#105
0#
#106
1#
b00011011 '
#107
0#
#108
1#
b00011100 '
#109
0#
#110
1#
b00011101 '
#111
0#
#112
1#
b00011110 '
#113
0#
#114
1#
b00011111 '
#115
0#
#116
1#
b00100000 '
#117
0#
#118
1#
b00100001 '
#119
0#
#120
1#
b00100010 '
#121
0#
#122
1#
b00100011 '
#123
0#
#124
1#
b00100100 '
#125
0#
#126
1#
b00100101 '
#127
0#
#128
1#
b00100110 '
#129
0#
#130
1#
b00100111 '
#131
0#
#132
1#
b00101000 '
#133
0#
#134
1#
b00101001 '
#135
0#
#136
1#
b00101010 '
#137
0#
#138
1#
b00101011 '
#139
0#
#140
1#
b00101100 '
#141
0#
#142
1#
b00101101 '
#143
0#
#144
1#
b00101110 '
#145
0#
#146
1#
b00101111 '
#147
0#
#148
1#
b00110000 '
#149
0#
#150
1#
b00110001 '
#151
0#
#152
1#
b00110010 '
#153
0#
#154
1#
b00110011 '
#155
0#
#156
1#
b00110100 '
#157
0#
#158
1#
b00110101 '
#159
0#
#160
1#
b00110110 '
#161
0#
#162
1#
b00110111 '
#163
0#
#164
1#
b00111000 '
#165
0#
#166
1#
b00111001 '
#167
0#
#168
1#
b00111010 '
#169
0#
#170
1#
b00111011 '
#171
0#
#172
1#
b00111100 '
#173
0#
#174
1#
b00111101 '
#175
0#
#176
1#
b00111110 '
#177
0#
#178
1#
b00111111 '
#179
0#
#180
1#
b01000000 '
#181
0#
#182
1#
b01000001 '
#183
0#
#184
1#
b01000010 '
#185
0#
#186
1#
b01000011 '
#187
0#
#188
1#
b01000100 '
#189
0#
#190
1#
b01000101 '
#191
0#
#192
1#
b01000110 '
#193
0#
#194
1#
b01000111 '
#195
0#
#196
1#
b01001000 '
#197
0#
#198
1#
b01001001 '
#199
0#
#200
1#
b01001010 '
#201
0#
#202
1#
b01001011 '
#203
0#
#204
1#
b01001100 '
#205
0#
#206
1#
b01001101 '
#207
0#
#208
1#
b01001110 '
#209
0#
#210
1#
b01001111 '
#211
0#
#212
1#
b01010000 '
#213
0#
#214
1#
b01010001 '
#215
0#
#216
1#
b01010010 '
#217
0#
#218
1#
b01010011 '
#219
0#
#220
1#
b01010100 '
#221
0#
#222
1#
b01010101 '
#223
0#
#224
1#
b01010110 '
#225
0#
#226
1#
b01010111 '
#227
0#
#228
1#
b01011000 '
#229
0#
#230
1#
b01011001 '
#231
0#
#232
1#
b01011010 '
#233
0#
#234
1#
b01011011 '
#235
0#
#236
1#
b01011100 '
#237
0#
#238
1#
b01011101 '
#239
0#
#240
1#
b01011110 '
#241
0#
#242
1#
b01011111 '
#243
0#
#244
1#
b01100000 '
#245
0#
#246
1#
b01100001 '
#247
0#
#248
1#
b01100010 '
#249
0#
#250
1#
b01100011 '
#251
0#
#252
1#
b01100100 '
#253
0#
#254
1#
b01100101 '
#255
0#
#256
1#
b01100110 '
#257
0#
#258
1#
b01100111 '
#259
0#
#260
1#
b01101000 '
#261
0#
#262
1#
b01101001 '
#263
0#
#264
1#
b01101010 '
#265
0#
#266
1#
b01101011 '
#267
0#
#268
1#
b01101100 '
#269
0#
#270
1#
b01101101 '
#271
0#
#272
1#
b01101110 '
#273
0#
#274
1#
b01101111 '
#275
0#
#276
1#
b01110000 '
#277
0#
#278
1#
b01110001 '
#279
0#
#280
1#
b01110010 '
#281
0#
#282
1#
b01110011 '
#283
0#
#284
1#
b01110100 '
#285
0#
#286
1#
b01110101 '
#287
0#
#288
1#
b01110110 '
#289
0#
#290
1#
b01110111 '
#291
0#
#292
1#
b01111000 '
#293
0#
#294
1#
b01111001 '
#295
0#
#296
1#
b01111010 '
#297
0#
#298
1#
b01111011 '
#299
0#
#300
1#
b01111100 '
#301
0#
#302
1#
b01111101 '
#303
0#
#304
1#
b01111110 '
#305
0#
#306
1#
b01111111 '
#307
0#
#308
1#
b10000000 '
#309
0#
#310
1#
b10000001 '
#311
0#
#312
1#
b10000010 '
#313
0#
#314
1#
b10000011 '
#315
0#
#316
1#
b10000100 '
#317
0#
#318
1#
b10000101 '
#319
0#
#320
1#
b10000110 '
#321
0#
#322
1#
b10000111 '
#323
0#
#324
1#
b10001000 '
#325
0#
#326
1#
b10001001 '
#327
0#
#328
1#
b10001010 '
#329
0#
#330
1#
b10001011 '
#331
0#
#332
1#
b10001100 '
#333
0#
#334
1#
b10001101 '
#335
0#
#336
1#
b10001110 '
#337
0#
#338
1#
b10001111 '
#339
0#
#340
1#
b10010000 '
#341
0#
#342
1#
b10010001 '
#343
0#
#344
1#
b10010010 '
#345
0#
#346
1#
b10010011 '
#347
0#
#348
1#
b10010100 '
#349
0#
#350
1#
b10010101 '
#351
0#
#352
1#
b10010110 '
#353
0#
#354
1#
b10010111 '
#355
0#
#356
1#
b10011000 '
#357
0#
#358
1#
b10011001 '
#359
0#
#360
1#
b10011010 '
#361
0#
#362
1#
b10011011 '
#363
0#
#364
1#
b10011100 '
#365
0#
#366
1#
b10011101 '
#367
0#
#368
1#
b10011110 '
#369
0#
#370
1#
b10011111 '
#371
0#
#372
1#
b10100000 '
#373
0#
#374
1#
b10100001 '
#375
0#
#376
1#
b10100010 '
#377
0#
#378
1#
b10100011 '
#379
0#
#380
1#
b10100100 '
#381
0#
#382
1#
b10100101 '
#383
0#
#384
1#
b10100110 '
#385
0#
#386
1#
b10100111 '
#387
0#
#388
1#
b10101000 '
#389
0#
#390
1#
b10101001 '
#391
0#
#392
1#
b10101010 '
#393
0#
#394
1#
b10101011 '
#395
0#
#396
1#
b10101100 '
#397
0#
#398
1#
b10101101 '
#399
0#
#400
1#
b10101110 '
#401
0#
#402
1#
b10101111 '
#403
0#
#404
1#
b10110000 '
#405
0#
#406
1#
b10110001 '
#407
0#
#408
1#
b10110010 '
#409
0#
#410
1#
b10110011 '
#411
0#
#412
1#
b10110100 '
#413
0#
#414
1#
b10110101 '
#415
0#
#416
1#
b10110110 '
#417
0#
#418
1#
b10110111 '
#419
0#
#420
1#
b10111000 '
#421
0#
#422
1#
b10111001 '
#423
0#
#424
1#
b10111010 '
#425
0#
#426
1#
b10111011 '
#427
0#
#428
1#
b10111100 '
#429
0#
#430
1#
b10111101 '
#431
0#
#432
1#
b10111110 '
#433
0#
#434
1#
b10111111 '
#435
0#
#436
1#
b11000000 '
#437
0#
#438
1#
b11000001 '
#439
0#
#440
1#
b11000010 '
#441
0#
#442
1#
b11000011 '
#443
0#
#444
1#
b11000100 '
#445
0#
#446
1#
b11000101 '
#447
0#
#448
1#
b11000110 '
#449
0#
#450
1#
b11000111 '
#451
0#
#452
1#
b11001000 '
#453
0#
#454
1#
b11001001 '
#455
0#
#456
1#
b11001010 '
#457
0#
#458
1#
b11001011 '
#459
0#
#460
1#
b11001100 '
#461
0#
#462
1#
b11001101 '
#463
0#
#464
1#
b11001110 '
#465
0#
#466
1#
b11001111 '
#467
0#
#468
1#
b11010000 '
#469
0#
#470
1#
b11010001 '
#471
0#
#472
1#
b11010010 '
#473
0#
#474
1#
b11010011 '
#475
0#
#476
1#
b11010100 '
#477
0#
#478
1#
b11010101 '
#479
0#
#480
1#
b11010110 '
#481
0#
#482
1#
b11010111 '
#483
0#
#484
1#
b11011000 '
#485
0#
#486
1#
b11011001 '
#487
0#
#488
1#
b11011010 '
#489
0#
#490
1#
b11011011 '
#491
0#
#492
1#
b11011100 '
#493
0#
#494
1#
b11011101 '
#495
0#
#496
1#
b11011110 '
#497
0#
#498
1#
b11011111 '
#499
0#
#500
1#
b11100000 '
#501
0#
#502
1#
b11100001 '
#503
0#
#504
1#
b11100010 '
#505
0#
#506
1#
b11100011 '
#507
0#
#508
1#
b11100100 '
#509
0#
#510
1#
b11100101 '
#511
0#
#512
1#
b11100110 '
#513
0#
#514
1#
b11100111 '
#515
0#
#516
1#
b11101000 '
#517
0#
#518
1#
b11101001 '
#519
0#
#520
1#
b11101010 '
#521
0#
#522
1#
b11101011 '
#523
0#
#524
1#
b11101100 '
#525
0#
#526
1#
b11101101 '
#527
0#
#528
1#
b11101110 '
#529
0#
#530
1#
b11101111 '
#531
0#
#532
1#
b11110000 '
#533
0#
#534
1#
1%
b11110001 '
#535
0#
#536
1#
0%
b00001000 '
#537
0#
#538
1#
1%
b00001001 '
#539
0#
#540
1#
0%
b00001000 '
#541
0#
#542
1#
b00001001 '
#543
0#
#544
1#
b00001010 '
#545
0#
#546
1#
b00001011 '
#547
0#
#548
1#
b00001100 '
#549
0#
#550
1#
1%
b00001101 '
#551
0#
#552
1#
0%
b00001000 '
#553
0#
#554
1#
b00001001 '
#555
0#
#556
1#
1%
b00001010 '
#557
0#
#558
1#
0%
b00001000 '
#559
0#
#560
1#
b00001001 '
#561
0#
#562
1#
b00001010 '
#563
0#
#564
1#
1%
b00001011 '
#565
0#
#566
1#
0%
b00001000 '
#567
0#
#568
1#
b00001001 '
#569
0#
#570
1#
b00001010 '
#571
0#
#572
1#
b00001011 '
#573
0#
#574
1#
1%
b00001100 '
#575
0#
#576
1#
0%
b00001000 '
#577
0#
#578
1#
b00001001 '
#579
0#
#580
1#
b00001010 '
#581
0#
#582
1#
b00001011 '
#583
0#
#584
1#
b00001100 '
#585
0#
#586
1#
b00001101 '
#587
0#
#588
1#
b00001110 '
#589
0#
#590
1#
b00001111 '
#591
0#
#592
1#
b00010000 '
#593
0#
#594
1#
b00010001 '
#595
0#
#596
1#
b00010010 '
#597
0#
#598
1#
b00010011 '
#599
0#
#600
1#
b00010100 '
#601
0#
#602
1#
b00010101 '
#603
0#
#604
1#
b00010110 '
#605
0#
#606
1#
b00010111 '
#607
0#
#608
1#
b00011000 '
#609
0#
#610
1#
b00011001 '
#611
0#
#612
1#
b00011010 '
#613
0#
#614
1#
b00011011 '
#615
0#
#616
1#
b00011100 '
#617
0#
#618
1#
b00011101 '
#619
0#
#620
1#
b00011110 '
#621
0#
#622
1#
b00011111 '
#623
0#
#624
1#
b00100000 '
#625
0#
#626
1#
b00100001 '
#627
0#
#628
1#
b00100010 '
#629
0#
#630
1#
b00100011 '
#631
0#
#632
1#
b00100100 '
#633
0#
#634
1#
b00100101 '
#635
0#
#636
1#
b00100110 '
#637
0#
#638
1#
b00100111 '
#639
0#
#640
1#
b00101000 '
#641
0#
#642
1#
b00101001 '
#643
0#
#644
1#
b00101010 '
#645
0#
#646
1#
b00101011 '
#647
0#
#648
1#
b00101100 '
#649
0#
#650
1#
b00101101 '
#651
0#
#652
1#
1%
b00101110 '
#653
0#
#654
1#
0%
b00001000 '
#655
0#
#656
1#
b00001001 '
#657
0#
#658
1#
b00001010 '
#659
0#
#660
1#
b00001011 '
#661
0#
#662
1#
b00001100 '
#663
0#
#664
1#
b00001101 '
#665
0#
#666
1#
b00001110 '
#667
0#
#668
1#
b00001111 '
#669
0#
#670
1#
b00010000 '
#671
0#
#672
1#
b00010001 '
#673
0#
#674
1#
b00010010 '
#675
0#
#676
1#
b00010011 '
#677
0#
#678
1#
b00010100 '
#679
0#
#680
1#
b00010101 '
#681
0#
#682
1#
b00010110 '
#683
0#
#684
1#
b00010111 '
#685
0#
#686
1#
b00011000 '
#687
0#
#688
1#
b00011001 '
#689
0#
#690
1#
b00011010 '
#691
0#
#692
1#
b00011011 '
#693
0#
#694
1#
b00011100 '
#695
0#
#696
1#
b00011101 '
#697
0#
#698
1#
1%
b00011110 '
#699
0#
#700
1#
0%
b00001000 '
#701
0#
#702
1#
b00001001 '
#703
0#
#704
1#
b00001010 '
#705
0#
#706
1#
b00001011 '
#707
0#
#708
1#
b00001100 '
#709
0#
#710
1#
b00001101 '
#711
0#
#712
1#
b00001110 '
#713
0#
#714
1#
b00001111 '
#715
0#
#716
1#
b00010000 '
#717
0#
#718
1#
b00010001 '
#719
0#
#720
1#
b00010010 '
#721
0#
#722
1#
b00010011 '
#723
0#
#724
1#
b00010100 '
#725
0#
#726
1#
b00010101 '
#727
0#
#728
1#
b00010110 '
#729
0#
#730
1#
b00010111 '
#731
0#
#732
1#
b00011000 '
#733
0#
#734
1#
b00011001 '
#735
0#
#736
1#
b00011010 '
#737
0#
#738
1#
b00011011 '
#739
0#
#740
1#
b00011100 '
#741
0#
#742
1#
b00011101 '
#743
0#
#744
1#
b00011110 '
#745
0#
#746
1#
b00011111 '
#747
0#
#748
1#
b00100000 '
#749
0#
#750
1#
b00100001 '
#751
0#
#752
1#
b00100010 '
#753
0#
#754
1#
b00100011 '
#755
0#
#756
1#
b00100100 '
#757
0#
#758
1#
1%
b00100101 '
#759
0#
#760
1#
0%
b00001000 '
#761
0#
#762
1#
b00001001 '
#763
0#
#764
1#
b00001010 '
#765
0#
#766
1#
b00001011 '
#767
0#
#768
1#
b00001100 '
#769
0#
#770
1#
b00001101 '
#771
0#
#772
1#
b00001110 '
#773
0#
#774
1#
b00001111 '
#775
0#
#776
1#
b00010000 '
#777
0#
#778
1#
b00010001 '
#779
0#
#780
1#
b00010010 '
#781
0#
#782
1#
b00010011 '
#783
0#
#784
1#
b00010100 '
#785
0#
#786
1#
b00010101 '
#787
0#
#788
1#
b00010110 '
#789
0#
#790
1#
b00010111 '
#791
0#
#792
1#
b00011000 '
#793
0#
#794
1#
b00011001 '
#795
0#
#796
1#
b00011010 '
#797
0#
#798
1#
b00011011 '
#799
0#
#800
1#
b00011100 '
#801
0#
#802
1#
b00011101 '
#803
0#
#804
1#
b00011110 '
#805
0#
#806
1#
b00011111 '
#807
0#
#808
1#
b00100000 '
#809
0#
#810
1#
b00100001 '
#811
0#
#812
1#
b00100010 '
#813
0#
#814
1#
b00100011 '
#815
0#
#816
1#
b00100100 '
#817
0#
#818
1#
b00100101 '
#819
0#
#820
1#
b00100110 '
#821
0#
#822
1#
b00100111 '
#823
0#
#824
1#
b00101000 '
#825
0#
#826
1#
b00101001 '
#827
0#
#828
1#
b00101010 '
#829
0#
#830
1#
b00101011 '
#831
0#
#832
1#
b00101100 '
#833
0#
#834
1#
b00101101 '
#835
0#
#836
1#
b00101110 '
#837
0#
#838
1#
b00101111 '
#839
0#
#840
1#
b00110000 '
#841
0#
#842
1#
b00110001 '
#843
0#
#844
1#
b00110010 '
#845
0#
#846
1#
b00110011 '
#847
0#
#848
1#
b00110100 '
#849
0#
#850
1#
b00110101 '
#851
0#
#852
1#
b00110110 '
#853
0#
#854
1#
b00110111 '
#855
0#
#856
1#
b00111000 '
#857
0#
#858
1#
b00111001 '
#859
0#
#860
1#
b00111010 '
#861
0#
#862
1#
b00111011 '
#863
0#
#864
1#
b00111100 '
#865
0#
#866
1#
b00111101 '
#867
0#
#868
1#
b00111110 '
#869
0#
#870
1#
b00111111 '
#871
0#
#872
1#
b01000000 '
#873
0#
#874
1#
b01000001 '
#875
0#
#876
1#
b01000010 '
#877
0#
#878
1#
b01000011 '
#879
0#
#880
1#
b01000100 '
#881
0#
#882
1#
b01000101 '
#883
0#
#884
1#
b01000110 '
#885
0#
#886
1#
b01000111 '
#887
0#
#888
1#
b01001000 '
#889
0#
#890
1#
b01001001 '
#891
0#
#892
1#
b01001010 '
#893
0#
#894
1#
b01001011 '
#895
0#
#896
1#
b01001100 '
#897
0#
#898
1#
b01001101 '
#899
0#
#900
1#
b01001110 '
#901
0#
#902
1#
b01001111 '
#903
0#
#904
1#
b01010000 '
#905
0#
#906
1#
b01010001 '
#907
0#
#908
1#
b01010010 '
#909
0#
#910
1#
b01010011 '
#911
0#
#912
1#
b01010100 '
#913
0#
#914
1#
b01010101 '
#915
0#
#916
1#
b01010110 '
#917
0#
#918
1#
b01010111 '
#919
0#
#920
1#
b01011000 '
#921
0#
#922
1#
b01011001 '
#923
0#
#924
1#
b01011010 '
#925
0#
#926
1#
b01011011 '
#927
0#
#928
1#
b01011100 '
#929
0#
#930
1#
b01011101 '
#931
0#
#932
1#
b01011110 '
#933
0#
#934
1#
b01011111 '
#935
0#
#936
1#
b01100000 '
#937
0#
#938
1#
b01100001 '
#939
0#
#940
1#
b01100010 '
#941
0#
#942
1#
b01100011 '
#943
0#
#944
1#
b01100100 '
#945
0#
#946
1#
b01100101 '
#947
0#
#948
1#
b01100110 '
#949
0#
#950
1#
b01100111 '
#951
0#
#952
1#
b01101000 '
#953
0#
#954
1#
b01101001 '
#955
0#
#956
1#
b01101010 '
#957
0#
#958
1#
b01101011 '
#959
0#
#960
1#
b01101100 '
#961
0#
#962
1#
b01101101 '
#963
0#
#964
1#
b01101110 '
#965
0#
#966
1#
b01101111 '
#967
0#
#968
1#
b01110000 '
#969
0#
#970
1#
b01110001 '
#971
0#
#972
1#
b01110010 '
#973
0#
#974
1#
b01110011 '
#975
0#
#976
1#
b01110100 '
#977
0#
#978
1#
b01110101 '
#979
0#
#980
1#
b01110110 '
#981
0#
#982
1#
b01110111 '
#983
0#
#984
1#
b01111000 '
#985
0#
#986
1#
b01111001 '
#987
0#
#988
1#
b01111010 '
#989
0#
#990
1#
b01111011 '
#991
0#
#992
1#
b01111100 '
#993
0#
#994
1#
b01111101 '
#995
0#
#996
1#
b01111110 '
#997
0#
#998
1#
b01111111 '
#999
0#
#1000
1#
b10000000 '
#1001
0#
#1002
1#
b10000001 '
#1003
0#
#1004
1#
b10000010 '
#1005
0#
#1006
1#
b10000011 '
#1007
0#
#1008
1#
b10000100 '
#1009
0#
#1010
1#
b10000101 '
#1011
0#
#1012
1#
b10000110 '
#1013
0#
#1014
1#
b10000111 '
#1015
0#
#1016
1#
b10001000 '
#1017
0#
#1018
1#
b10001001 '
#1019
0#
#1020
1#
b10001010 '
#1021
0#
#1022
1#
b10001011 '
#1023
0#
#1024
1#
b10001100 '
#1025
0#
#1026
1#
b10001101 '
#1027
0#
#1028
1#
b10001110 '
#1029
0#
#1030
1#
b10001111 '
#1031
0#
#1032
1#
b10010000 '
#1033
0#
#1034
1#
b10010001 '
#1035
0#
#1036
1#
b10010010 '
#1037
0#
#1038
1#
b10010011 '
#1039
0#
#1040
1#
b10010100 '
#1041
0#
#1042
1#
b10010101 '
#1043
0#
#1044
1#
b10010110 '
#1045
0#
#1046
1#
b10010111 '
#1047
0#
#1048
1#
b10011000 '
#1049
0#
#1050
1#
b10011001 '
#1051
0#
#1052
1#
b10011010 '
#1053
0#
#1054
1#
b10011011 '
#1055
0#
#1056
1#
b10011100 '
#1057
0#
#1058
1#
b10011101 '
#1059
0#
#1060
1#
b10011110 '
#1061
0#
#1062
1#
b10011111 '
#1063
0#
#1064
1#
b10100000 '
#1065
0#
#1066
1#
b10100001 '
#1067
0#
#1068
1#
b10100010 '
#1069
0#
#1070
1#
b10100011 '
#1071
0#
#1072
1#
b10100100 '
#1073
0#
#1074
1#
b10100101 '
#1075
0#
#1076
1#
b10100110 '
#1077
0#
#1078
1#
b10100111 '
#1079
0#
#1080
1#
b10101000 '
#1081
0#
#1082
1#
b10101001 '
#1083
0#
#1084
1#
b10101010 '
#1085
0#
#1086
1#
b10101011 '
#1087
0#
#1088
1#
b10101100 '
#1089
0#
#1090
1#
b10101101 '
#1091
0#
#1092
1#
b10101110 '
#1093
0#
#1094
1#
b10101111 '
#1095
0#
#1096
1#
b10110000 '
#1097
0#
#1098
1#
b10110001 '
#1099
0#
#1100
1#
b10110010 '
#1101
0#
#1102
1#
b10110011 '
#1103
0#
#1104
1#
b10110100 '
#1105
0#
#1106
1#
b10110101 '
#1107
0#
#1108
1#
b10110110 '
#1109
0#
#1110
1#
b10110111 '
#1111
0#
#1112
1#
b10111000 '
#1113
0#
#1114
1#
b10111001 '
#1115
0#
#1116
1#
b10111010 '
#1117
0#
#1118
1#
b10111011 '
#1119
0#
#1120
1#
b10111100 '
#1121
0#
#1122
1#
b10111101 '
#1123
0#
#1124
1#
b10111110 '
#1125
0#
#1126
1#
b10111111 '
#1127
0#
#1128
1#
b11000000 '
#1129
0#
#1130
1#
b11000001 '
#1131
0#
#1132
1#
b11000010 '
#1133
0#
#1134
1#
b11000011 '
#1135
0#
#1136
1#
b11000100 '
#1137
0#
#1138
1#
b11000101 '
#1139
0#
#1140
1#
b11000110 '
#1141
0#
#1142
1#
b11000111 '
#1143
0#
#1144
1#
b11001000 '
#1145
0#
#1146
1#
b11001001 '
#1147
0#
#1148
1#
b11001010 '
#1149
0#
#1150
1#
b11001011 '
#1151
0#
#1152
1#
b11001100 '
#1153
0#
#1154
1#
b11001101 '
#1155
0#
#1156
1#
b11001110 '
#1157
0#
#1158
1#
b11001111 '
#1159
0#
#1160
1#
b11010000 '
#1161
0#
#1162
1#
b11010001 '
#1163
0#
#1164
1#
b11010010 '
#1165
0#
#1166
1#
b11010011 '
#1167
0#
#1168
1#
b11010100 '
#1169
0#
#1170
1#
b11010101 '
#1171
0#
#1172
1#
b11010110 '
#1173
0#
#1174
1#
b11010111 '
#1175
0#
#1176
1#
b11011000 '
#1177
0#
#1178
1#
b11011001 '
#1179
0#
#1180
1#
b11011010 '
#1181
0#
#1182
1#
b11011011 '
#1183
0#
#1184
1#
b11011100 '
#1185
0#
#1186
1#
b11011101 '
#1187
0#
#1188
1#
b11011110 '
#1189
0#
#1190
1#
b11011111 '
#1191
0#
#1192
1#
b11100000 '
#1193
0#
#1194
1#
b11100001 '
#1195
0#
#1196
1#
b11100010 '
#1197
0#
#1198
1#
b11100011 '
#1199
0#
#1200
1#
b11100100 '
#1201
0#
#1202
1#
b11100101 '
#1203
0#
#1204
1#
b11100110 '
#1205
0#
#1206
1#
b11100111 '
#1207
0#
#1208
1#
b11101000 '
#1209
0#
#1210
1#
b11101001 '
#1211
0#
#1212
1#
b11101010 '
#1213
0#
#1214
1#
b11101011 '
#1215
0#
#1216
1#
b11101100 '
#1217
0#
#1218
1#
b11101101 '
#1219
0#
#1220
1#
b11101110 '
#1221
0#
#1222
1#
b11101111 '
#1223
0#
#1224
1#
b11110000 '
#1225
0#
#1226
1#
b11110001 '
#1227
0#
#1228
1#
b11110010 '
#1229
0#
#1230
1#
b11110011 '
#1231
0#
#1232
1#
b11110100 '
#1233
0#
#1234
1#
b11110101 '
#1235
0#
#1236
1#
b11110110 '
#1237
0#
#1238
1#
b11110111 '
#1239
0#
#1240
1#
b11111000 '
#1241
0#
#1242
1#
b11111001 '
#1243
0#
#1244
1#
b11111010 '
#1245
0#
#1246
1#
b11111011 '
#1247
0#
#1248
1#
b11111100 '
#1249
0#
#1250
1#
b11111101 '
#1251
0#
#1252
1#
b11111110 '
#1253
0#
#1254
1#
b11111111 '
#1255
0#
#1256
1#
b00000000 '
#1257
0#
#1258
1#
b00000001 '
#1259
0#
#1260
1#
b00000010 '
#1261
0#
#1262
1#
b00000011 '
#1263
0#
#1264
1#
b00000100 '
#1265
0#
#1266
1#
b00000101 '
#1267
0#
#1268
1#
b00000110 '
#1269
0#
#1270
1#
b00000111 '
#1271
0#
#1272
1#
b00001000 '
#1273
0#
#1274
1#
b00001001 '
#1275
0#
#1276
1#
b00001010 '
#1277
0#
#1278
1#
b00001011 '
#1279
0#
#1280
1#
b00001100 '
#1281
0#
#1282
1#
b00001101 '
#1283
0#
#1284
1#
b00001110 '
#1285
0#
#1286
1#
b00001111 '
#1287
0#
#1288
1#
b00010000 '
#1289
0#
#1290
1#
b00010001 '
#1291
0#
#1292
1#
b00010010 '
#1293
0#
#1294
1#
b00010011 '
#1295
0#
#1296
1#
b00010100 '
#1297
0#
#1298
1#
b00010101 '
#1299
0#
#1300
1#
b00010110 '
#1301
0#
#1302
1#
b00010111 '
#1303
0#
#1304
1#
b00011000 '
#1305
0#
#1306
1#
b00011001 '
#1307
0#
#1308
1#
b00011010 '
#1309
0#
#1310
1#
b00011011 '
#1311
0#
#1312
1#
b00011100 '
#1313
0#
#1314
1#
b00011101 '
#1315
0#
#1316
1#
b00011110 '
#1317
0#
#1318
1#
b00011111 '
#1319
0#
#1320
1#
b00100000 '
#1321
0#
#1322
1#
b00100001 '
#1323
0#
#1324
1#
b00100010 '
#1325
0#
#1326
1#
b00100011 '
#1327
0#
#1328
1#
b00100100 '
#1329
0#
#1330
1#
b00100101 '
#1331
0#
#1332
1#
b00100110 '
#1333
0#
#1334
1#
b00100111 '
#1335
0#
#1336
1#
b00101000 '
#1337
0#
#1338
1#
b00101001 '
#1339
0#
#1340
1#
b00101010 '
#1341
0#
#1342
1#
b00101011 '
#1343
0#
#1344
1#
b00101100 '
#1345
0#
#1346
1#
b00101101 '
#1347
0#
#1348
1#
b00101110 '
#1349
0#
#1350
1#
b00101111 '
#1351
0#
#1352
1#
b00110000 '
#1353
0#
#1354
1#
b00110001 '
#1355
0#
#1356
1#
b00110010 '
#1357
0#
#1358
1#
b00110011 '
#1359
0#
#1360
1#
b00110100 '
#1361
0#
#1362
1#
b00110101 '
#1363
0#
#1364
1#
b00110110 '
#1365
0#
#1366
1#
b00110111 '
#1367
0#
#1368
1#
b00111000 '
#1369
0#
#1370
1#
b00111001 '
#1371
0#
#1372
1#
b00111010 '
#1373
0#
#1374
1#
b00111011 '
#1375
0#
#1376
1#
b00111100 '
#1377
0#
#1378
1#
b00111101 '
#1379
0#
#1380
1#
b00111110 '
#1381
0#
#1382
1#
b00111111 '
#1383
0#
#1384
1#
b01000000 '
#1385
0#
#1386
1#
b01000001 '
#1387
0#
#1388
1#
b01000010 '
#1389
0#
#1390
1#
b01000011 '
#1391
0#
#1392
1#
b01000100 '
#1393
0#
#1394
1#
b01000101 '
#1395
0#
#1396
1#
b01000110 '
#1397
0#
#1398
1#
b01000111 '
#1399
0#
#1400
1#
b01001000 '
#1401
0#
#1402
1#
b01001001 '
#1403
0#
#1404
1#
b01001010 '
#1405
0#
#1406
1#
b01001011 '
#1407
0#
#1408
1#
b01001100 '
#1409
0#
#1410
1#
b01001101 '
#1411
0#
#1412
1#
b01001110 '
#1413
0#
#1414
1#
b01001111 '
#1415
0#
#1416
1#
b01010000 '
#1417
0#
#1418
1#
b01010001 '
#1419
0#
#1420
1#
b01010010 '
#1421
0#
#1422
1#
b01010011 '
#1423
0#
#1424
1#
b01010100 '
#1425
0#
#1426
1#
b01010101 '
#1427
0#
#1428
1#
b01010110 '
#1429
0#
#1430
1#
b01010111 '
#1431
0#
#1432
1#
b01011000 '
#1433
0#
#1434
1#
b01011001 '
#1435
0#
#1436
1#
b01011010 '
#1437
0#
#1438
1#
b01011011 '
#1439
0#
#1440
1#
b01011100 '
#1441
0#
#1442
1#
b01011101 '
#1443
0#
#1444
1#
b01011110 '
#1445
0#
#1446
1#
b01011111 '
#1447
0#
#1448
1#
b01100000 '
#1449
0#
#1450
1#
b01100001 '
#1451
0#
#1452
1#
b01100010 '
#1453
0#
#1454
1#
b01100011 '
#1455
0#
#1456
1#
b01100100 '
#1457
0#
#1458
1#
b01100101 '
#1459
0#
#1460
1#
b01100110 '
#1461
0#
#1462
1#
b01100111 '
#1463
0#
